trelis/__init__.py
trelis/_version.py
trelis-1.3.0.data/data/share/jupyter/labextensions/trelis-jupyter-assistant/package.json
trelis-1.3.0.data/data/share/jupyter/labextensions/trelis-jupyter-assistant/schemas/trelis-jupyter-assistant/package.json.orig
trelis-1.3.0.data/data/share/jupyter/labextensions/trelis-jupyter-assistant/schemas/trelis-jupyter-assistant/plugin.json
trelis-1.3.0.data/data/share/jupyter/labextensions/trelis-jupyter-assistant/static/564.812cdadb5b2339640bf3.js
trelis-1.3.0.data/data/share/jupyter/labextensions/trelis-jupyter-assistant/static/728.1918c88d90b6e9e6d1af.js
trelis-1.3.0.data/data/share/jupyter/labextensions/trelis-jupyter-assistant/static/remoteEntry.47ca20cdbd631f33fd49.js
trelis-1.3.0.data/data/share/jupyter/labextensions/trelis-jupyter-assistant/static/style.js
trelis-1.3.0.data/data/share/jupyter/labextensions/trelis-jupyter-assistant/static/third-party-licenses.json
trelis-1.3.0.data/data/share/jupyter/labextensions/trelis-jupyter-assistant/install.json
trelis-1.3.0.dist-info/METADATA
trelis-1.3.0.dist-info/WHEEL
trelis-1.3.0.dist-info/licenses/LICENSE
trelis-1.3.0.dist-info/RECORD
