Metadata-Version: 2.3
Name: trelis
Version: 1.3.0
Summary: A JupyterLab Code Assistant
Project-URL: Homepage, https://trelis.com/jupyter-assistant
Project-URL: Bug Tracker, https://trelis.com/jupyter-assistant
Project-URL: Repository, https://github.com/TrelisResearch/trelis-jupyter-assistant.git
Author-email: Trelis Research / Ronan McGovern <hello@trelis.com>
License: Trelis Assistant for Jupyter Lab - Proprietary License
License-File: LICENSE
Keywords: jupyter,jupyterlab,jupyterlab-extension
Classifier: Framework :: Jupyter
Classifier: Framework :: Jupyter :: JupyterLab
Classifier: Framework :: Jupyter :: JupyterLab :: 4
Classifier: Framework :: Jupyter :: JupyterLab :: Extensions
Classifier: Framework :: Jupyter :: JupyterLab :: Extensions :: Prebuilt
Classifier: Programming Language :: Python
Classifier: Programming Language :: Python :: 3
Classifier: Programming Language :: Python :: 3.8
Classifier: Programming Language :: Python :: 3.9
Classifier: Programming Language :: Python :: 3.10
Classifier: Programming Language :: Python :: 3.11
Classifier: Programming Language :: Python :: 3.12
Requires-Python: >=3.8
